hyperprompts/__init__.py
hyperprompts/core.py
hyperprompts-0.1.0.dist-info/METADATA
hyperprompts-0.1.0.dist-info/WHEEL
hyperprompts-0.1.0.dist-info/RECORD
