Metadata-Version: 2.1
Name: hyperprompts
Version: 0.1.0
Summary: A lightweight prompt template system for LLM-based projects
Home-page: https://github.com/gilad-rubin/hyperprompts
License: MIT
Keywords: prompt,template,ai,llm,hyperprompts
Author: Gillad Rubin
Author-email: gilad.rubin@gmail.com
Requires-Python: >=3.10,<4.0
Classifier: License :: OSI Approved :: MIT License
Classifier: Programming Language :: Python :: 3
Classifier: Programming Language :: Python :: 3.10
Classifier: Programming Language :: Python :: 3.11
Classifier: Programming Language :: Python :: 3.12
Project-URL: Repository, https://github.com/gilad-rubin/hyperprompts
